odoo/addons/product_search_by_display_name/README.rst
odoo/addons/product_search_by_display_name/__init__.py
odoo/addons/product_search_by_display_name/__manifest__.py
odoo/addons/product_search_by_display_name/i18n/es.po
odoo/addons/product_search_by_display_name/i18n/it.po
odoo/addons/product_search_by_display_name/i18n/product_search_by_display_name.pot
odoo/addons/product_search_by_display_name/models/__init__.py
odoo/addons/product_search_by_display_name/models/product_product.py
odoo/addons/product_search_by_display_name/models/product_template.py
odoo/addons/product_search_by_display_name/readme/CONTRIBUTORS.rst
odoo/addons/product_search_by_display_name/readme/CREDITS.rst
odoo/addons/product_search_by_display_name/readme/DESCRIPTION.rst
odoo/addons/product_search_by_display_name/static/description/icon.png
odoo/addons/product_search_by_display_name/static/description/index.html
odoo/addons/product_search_by_display_name/tests/__init__.py
odoo/addons/product_search_by_display_name/tests/test_product_search_by_display_name.py
odoo/addons/product_search_by_display_name/views/product_template.xml
odoo14_addon_product_search_by_display_name-14.0.1.0.1.dev6.dist-info/METADATA
odoo14_addon_product_search_by_display_name-14.0.1.0.1.dev6.dist-info/WHEEL
odoo14_addon_product_search_by_display_name-14.0.1.0.1.dev6.dist-info/top_level.txt
odoo14_addon_product_search_by_display_name-14.0.1.0.1.dev6.dist-info/RECORD
